QHotReload/__init__.py
QHotReload-0.2.1.dist-info/LICENSE
QHotReload-0.2.1.dist-info/METADATA
QHotReload-0.2.1.dist-info/WHEEL
QHotReload-0.2.1.dist-info/top_level.txt
QHotReload-0.2.1.dist-info/RECORD
