Metadata-Version: 2.1
Name: QHotReload
Version: 0.2.1
Summary: Hot relading tool for PySide and PyQt
Home-page: https://github.com/AtticRat/PyQHotReload
Author: Attic
Author-email: mornorrisjie@gmail.com
License: MIT
Classifier: Development Status :: 3 - Alpha
Classifier: Intended Audience :: Developers
Classifier: License :: OSI Approved :: MIT License
Classifier: Programming Language :: Python
Classifier: Programming Language :: Python :: 3
Classifier: Programming Language :: Python :: 3.6
Classifier: Programming Language :: Python :: 3.7
Classifier: Programming Language :: Python :: 3.8
Classifier: Programming Language :: Python :: 3.9
Classifier: Programming Language :: Python :: 3.10
License-File: LICENSE
Requires-Dist: qtpy
